dynamic_business_rules/__init__.py
dynamic_business_rules/admin.py
dynamic_business_rules/apps.py
dynamic_business_rules/forms.py
dynamic_business_rules/models.py
dynamic_business_rules/tests.py
dynamic_business_rules/views.py
dynamic_business_rules/migrations/0001_initial.py
dynamic_business_rules/migrations/0002_auto_20180930_0117.py
dynamic_business_rules/migrations/__init__.py
django_dynamic_business_rules-0.1.2.dist-info/AUTHORS.rst
django_dynamic_business_rules-0.1.2.dist-info/LICENSE
django_dynamic_business_rules-0.1.2.dist-info/METADATA
django_dynamic_business_rules-0.1.2.dist-info/WHEEL
django_dynamic_business_rules-0.1.2.dist-info/top_level.txt
django_dynamic_business_rules-0.1.2.dist-info/RECORD
