Metadata-Version: 2.1
Name: django-dynamic-business-rules
Version: 0.1.2
Summary: A Django centric event driven rules engine for extensible and configurable responses to changes to django models and triggers.
Home-page: https://github.com/adamhaney/django-dynamic-business-rules
Author: Adam Haney
Author-email: adam.jacob.haney@gmail.com
License: MIT
Keywords: django-dynamic-business-rules
Platform: UNKNOWN
Classifier: Development Status :: 3 - Alpha
Classifier: Framework :: Django :: 2.0
Classifier: Intended Audience :: Developers
Classifier: License :: OSI Approved :: BSD License
Classifier: Natural Language :: English
Classifier: Programming Language :: Python :: 2
Classifier: Programming Language :: Python :: 2.7
Classifier: Programming Language :: Python :: 3
Classifier: Programming Language :: Python :: 3.4
Classifier: Programming Language :: Python :: 3.5
Classifier: Programming Language :: Python :: 3.6
Requires-Dist: django-model-utils (>=2.0)
Requires-Dist: django-extensions (==2.1.0)
